dwarfbind/__init__.py
dwarfbind/cli.py
dwarfbind/debug_info.py
dwarfbind/generator.py
dwarfbind/identifiers.py
dwarfbind/logging.py
dwarfbind/output.py
dwarfbind/paths.py
dwarfbind/pkgconfig.py
dwarfbind/preprocessor.py
dwarfbind/progress.py
dwarfbind-0.1.4.dist-info/METADATA
dwarfbind-0.1.4.dist-info/WHEEL
dwarfbind-0.1.4.dist-info/entry_points.txt
dwarfbind-0.1.4.dist-info/licenses/LICENSE
dwarfbind-0.1.4.dist-info/RECORD
