Metadata-Version: 2.4
Name: dwarfbind
Version: 0.1.4
Summary: Generate Python ctypes bindings from shared libraries
Author-email: Ray Strode <rstrode@redhat.com>
License: MIT
License-File: LICENSE
Requires-Python: >=3.12
Requires-Dist: colorama>=0.4.6
Requires-Dist: pyelftools>=0.32
